PDAnalysis_fit/__init__.py
PDAnalysis_fit/_version.py
PDAnalysis_fit/core.py
PDAnalysis_fit/example.py
PDAnalysis_fit/utilities.py
PDAnalysis_fit-0.4.9.dist-info/LICENSE
PDAnalysis_fit-0.4.9.dist-info/METADATA
PDAnalysis_fit-0.4.9.dist-info/WHEEL
PDAnalysis_fit-0.4.9.dist-info/top_level.txt
PDAnalysis_fit-0.4.9.dist-info/RECORD
