Metadata-Version: 2.1
Name: PDAnalysis_fit
Version: 0.4.9
Summary: Package for Proccessing PD Data
Maintainer: Xanadu Inc.
License: MIT License
Classifier: Intended Audience :: Science/Research
Classifier: License :: OSI Approved :: Apache Software License
Classifier: Natural Language :: English
Classifier: Operating System :: POSIX
Classifier: Operating System :: MacOS :: MacOS X
Classifier: Operating System :: POSIX :: Linux
Classifier: Operating System :: Microsoft :: Windows
Classifier: Programming Language :: Python
Classifier: Programming Language :: Python :: 3
Classifier: Programming Language :: Python :: 3.8
Classifier: Programming Language :: Python :: 3.9
Classifier: Programming Language :: Python :: 3 :: Only
Classifier: Topic :: Scientific/Engineering :: Physics
Provides: PDAnalysis_fit
Requires-Python: >3.8.0
License-File: LICENSE
Requires-Dist: numpy >=1.20.3
Requires-Dist: scipy >=1.6.3
Requires-Dist: lmfit >=1.0.3
Requires-Dist: matplotlib >=3.4.2
Requires-Dist: pandas >=1.2.4
Requires-Dist: s3fs[boto3]
Requires-Dist: xarray
Requires-Dist: zarr >=2.10.1
